aiogram_translation/__init__.py
aiogram_translation/_translator.py
aiogram_translation/errors.py
aiogram_translation/middlewares/TranslationMiddleware.py
aiogram_translation/middlewares/__init__.py
aiogram_translation/models.py
aiogram_translation-2.0.1.dist-info/LICENSE
aiogram_translation-2.0.1.dist-info/METADATA
aiogram_translation-2.0.1.dist-info/WHEEL
aiogram_translation-2.0.1.dist-info/RECORD
