Metadata-Version: 2.1
Name: aiogram-translation
Version: 2.0.1
Summary: Simple aiogram translation plugin built using pydantic.
Home-page: https://github.com/barabum0/aiogram-translation
License: MIT
Keywords: python,aiogram,telegram,pydantic,translation
Author: Roman Poltorabatko
Author-email: barabum@duck.com
Requires-Python: >=3.10,<4.0
Classifier: Intended Audience :: Developers
Classifier: License :: OSI Approved :: MIT License
Classifier: Operating System :: OS Independent
Classifier: Programming Language :: Python
Classifier: Programming Language :: Python :: 3
Classifier: Programming Language :: Python :: 3.10
Classifier: Programming Language :: Python :: 3.11
Classifier: Programming Language :: Python :: 3.12
Classifier: Topic :: Software Development :: Libraries :: Python Modules
Requires-Dist: aiogram (>=3)
Requires-Dist: pydantic (>=2.5.2,<3.0.0)
Project-URL: Repository, https://github.com/barabum0/aiogram-translation
Project-URL: bug_tracker, https://github.com/barabum0/aiogram-translation/issues
Project-URL: source, https://github.com/barabum0/aiogram-translation
